mphelper/__init__.py
mphelper-0.0.3.dist-info/METADATA
mphelper-0.0.3.dist-info/WHEEL
mphelper-0.0.3.dist-info/top_level.txt
mphelper-0.0.3.dist-info/RECORD
